neumann/__init__.py
neumann/arraysetops.py
neumann/decorate.py
neumann/hist.py
neumann/logical.py
neumann/numint.py
neumann/utils.py
neumann/approx/__init__.py
neumann/approx/func.py
neumann/approx/lagrange.py
neumann/approx/mls.py
neumann/function/__init__.py
neumann/function/constraint.py
neumann/function/function.py
neumann/function/functions.py
neumann/function/metafunction.py
neumann/function/relation.py
neumann/function/testfunction.py
neumann/linalg/__init__.py
neumann/linalg/abstract.py
neumann/linalg/exceptions.py
neumann/linalg/frame.py
neumann/linalg/imap.py
neumann/linalg/meta.py
neumann/linalg/solve.py
neumann/linalg/tensor.py
neumann/linalg/testing.py
neumann/linalg/tr.py
neumann/linalg/utils.py
neumann/linalg/vector.py
neumann/linalg/frontal/__init__.py
neumann/linalg/frontal/frontal.py
neumann/linalg/frontal/frutils.py
neumann/linalg/frontal/path.py
neumann/linalg/frontal/postproc.py
neumann/linalg/frontal/proc.py
neumann/linalg/frontal/topo.py
neumann/linalg/sparse/__init__.py
neumann/linalg/sparse/csr.py
neumann/linalg/sparse/jaggedarray.py
neumann/linalg/sparse/utils.py
neumann/optimize/__init__.py
neumann/optimize/errors.py
neumann/optimize/ga.py
neumann/optimize/lp.py
neumann/topology/__init__.py
neumann/topology/graph.py
neumann-1.0.7.dist-info/LICENSE
neumann-1.0.7.dist-info/METADATA
neumann-1.0.7.dist-info/WHEEL
neumann-1.0.7.dist-info/top_level.txt
neumann-1.0.7.dist-info/RECORD
