Metadata-Version: 2.1
Name: neumann
Version: 1.0.7
Summary: A Python Library for Applied Mathematics in Physical Sciences.
Home-page: https://github.com/dewloosh/Neumann
Download-URL: https://github.com/dewloosh/Neumann/archive/refs/tags/1.0.7.zip
Author: Bence Balogh
Author-email: dewloosh@gmail.com
Classifier: Development Status :: 5 - Production/Stable
Classifier: License :: OSI Approved :: MIT License
Classifier: Programming Language :: Python :: 3.7
Classifier: Programming Language :: Python :: 3.8
Classifier: Programming Language :: Python :: 3.9
Classifier: Programming Language :: Python :: 3.10
Classifier: Programming Language :: Python :: 3 :: Only
Classifier: Operating System :: OS Independent
Classifier: Topic :: Scientific/Engineering
Classifier: Topic :: Scientific/Engineering :: Mathematics
Classifier: Topic :: Scientific/Engineering :: Physics
Requires-Python: >=3.7, <3.11
License-File: LICENSE
Requires-Dist: dewloosh.core (>=1.0.21)
Requires-Dist: linkeddeepdict (>=1.1.0)
Requires-Dist: numba (>=0.56.4)
Requires-Dist: numpy (==1.23.5)
Requires-Dist: scipy (>=1.9.3)
Requires-Dist: awkward (>=2.0.8)
Requires-Dist: sympy (>=1.11.1)
